{
  "games": {
    "roulette": {
      "name": "Roulette Shots",
      "description": "A Shot Roulette game",
      "image": "/assets/img/roulette.jpeg",
      "version": "1.0.0"
    },
    "liar": {
      "name": "Liar Liar Liar!",
      "description": "A Counter of Liar game",
      "image": "/assets/img/liar.jpg",
      "version": "1.0.0"
    },
    "test": {
      "name": "Test Name Game",
      "description": "Test Description Game",
      "image": "/assets/img/no-img-placeholder.png",
      "version": "alpha-beta-omega"
    }
  }
}